kuaidi100_mcp/__init__.py
kuaidi100_mcp/__main__.py
kuaidi100_mcp/api_mcp.py
iflow_mcp_kuaidi100_mcp-0.1.3.dist-info/METADATA
iflow_mcp_kuaidi100_mcp-0.1.3.dist-info/WHEEL
iflow_mcp_kuaidi100_mcp-0.1.3.dist-info/entry_points.txt
iflow_mcp_kuaidi100_mcp-0.1.3.dist-info/licenses/LICENSE
iflow_mcp_kuaidi100_mcp-0.1.3.dist-info/RECORD
