Metadata-Version: 2.4
Name: iflow-mcp_kuaidi100-mcp
Version: 0.1.3
Summary: 快递100推出了国内首个兼容MCP协议的物流信息服务平台—快递100 MCP Server。 快递100旗下百递云·API开放平台的核心API服务现已全面支持MCP协议。开发者简单配置即可快速接入快递查询、运费预估、智能时效预估（含全程与在途模式）等核心功能。
Project-URL: HomeUrl, https://github.com/kuaidi100-api/kuaidi100-MCP
License:                                  Apache License
License-File: LICENSE
Keywords: delivery,express,kuaidi100,logistics,mcp
Classifier: License :: OSI Approved :: Apache Software License
Classifier: Operating System :: OS Independent
Classifier: Programming Language :: Python :: 3.11
Requires-Python: >=3.11
Requires-Dist: httpx>=0.25.0
Requires-Dist: mcp>=1.0.0
